README.rst
setup.py
amanita/__init__.py
amanita/__main__.py
amanita/amanita.py
amanita.egg-info/PKG-INFO
amanita.egg-info/SOURCES.txt
amanita.egg-info/dependency_links.txt
amanita.egg-info/entry_points.txt
amanita.egg-info/not-zip-safe
amanita.egg-info/top_level.txt