Metadata-Version: 1.1
Name: amanita
Version: 0.0.1
Summary: Create python customizable projects
Home-page: https://github.com/constrict0r/amanita
Author: constrict0r
Author-email: constrict0r@protonmail.com
License: MIT
Platform: UNKNOWN
Classifier: Development Status :: 2 - Pre-Alpha
Classifier: Topic :: Software Development :: Build Tools
Classifier: License :: OSI Approved :: MIT License
Classifier: Programming Language :: Python
Classifier: Programming Language :: Python :: 2
Classifier: Programming Language :: Python :: 2.7
Classifier: Programming Language :: Python :: 3
Classifier: Programming Language :: Python :: 3.5
